{
  "enclosure" : {
    "length" : "36383725",
    "type" : "audio/mpeg",
    "url" : "https://anchor.fm/s/3b2be68/podcast/play/899473/https%3A%2F%2Fd3ctxlq1ktw2nl.cloudfront.net%2Fproduction%2F2018-6-13%2F3603249-44100-1-0d3b38bd2dc6.mp3"
  },
  "itunes:summary" : "Candice encourages Casey to be kinder to himself today about tough situations in the past; if only she could get a word in through all the giggles.",
  "dc:creator" : "Casey Neistat and Candice Pool",
  "pubDate" : "Fri, 13 Jul 2018 20:19:14 GMT",
  "itunes:duration" : "2989",
  "itunes:explicit" : "Yes",
  "itunes:episodeType" : "full",
  "title" : "Be Forgiving",
  "link" : "https://ct.fm/episodes/Be-Forgiving-e1puuh",
  "itunes:episode" : "8",
  "itunes:image" : "https://d3t3ozftmdmh3i.cloudfront.net/production/podcast_uploaded_nologo/520458/520458-1529077783947-a645a049d7d78.jpg",
  "guid" : "7c160f44-a472-9aad-c494-1d8cea91c0f9",
  "description" : "Candice encourages Casey to be kinder to himself today about tough situations in the past; if only she could get a word in through all the giggles.\n",
  "itunes:season" : "1"
}